kindcleaner/__init__.py
kindcleaner-0.1.dist-info/LICENSE
kindcleaner-0.1.dist-info/METADATA
kindcleaner-0.1.dist-info/WHEEL
kindcleaner-0.1.dist-info/top_level.txt
kindcleaner-0.1.dist-info/RECORD
