Metadata-Version: 2.1
Name: kindcleaner
Version: 0.1
Summary: Data cleaning package
Home-page: https://github.com/innlouvate/kindcleaner
Author: innlouvate
Author-email: franklin@thoughtworks.com
License: UNKNOWN
Platform: UNKNOWN
Classifier: Programming Language :: Python :: 3
Classifier: License :: OSI Approved :: MIT License
Classifier: Operating System :: OS Independent
